ams_sdk/__init__.py
ams_sdk/client.py
ams_sdk/utils.py
ams_sdk-1.0.7.dist-info/LICENSE
ams_sdk-1.0.7.dist-info/METADATA
ams_sdk-1.0.7.dist-info/WHEEL
ams_sdk-1.0.7.dist-info/RECORD
